[
  {"company_id": 1, "title": "Series D funding round closed", "source": "TechCrunch", "published_date": "2026-01-15", "summary": "Closed a $80M Series D round led by growth investors to accelerate enterprise expansion.", "category": "funding"},
  {"company_id": 2, "title": "Expansion into European markets", "source": "SaaStr", "published_date": "2026-02-01", "summary": "Announced entry into UK and DACH markets with new London office.", "category": "partnership"},
  {"company_id": 3, "title": "New AI-powered threat detection module", "source": "Dark Reading", "published_date": "2026-01-20", "summary": "Launched next-gen AI module that reduces false positives by 85%.", "category": "product"},
  {"company_id": 4, "title": "Raises $55M Growth Round", "source": "Crunchbase News", "published_date": "2025-12-10", "summary": "Growth round to fund product development and sales team expansion.", "category": "funding"},
  {"company_id": 5, "title": "Partners with major hospital network", "source": "Healthcare IT News", "published_date": "2026-01-28", "summary": "Signed multi-year deal with 200+ hospital system for clinical workflow automation.", "category": "partnership"},
  {"company_id": 6, "title": "Achieves SOC 2 Type II certification", "source": "SecurityWeek", "published_date": "2025-11-15", "summary": "Completed SOC 2 Type II audit, unlocking enterprise sales pipeline.", "category": "product"},
  {"company_id": 7, "title": "Hires ex-Salesforce CRO", "source": "LinkedIn", "published_date": "2026-02-10", "summary": "New CRO brings 15 years of enterprise sales leadership experience.", "category": "hiring"},
  {"company_id": 8, "title": "Launches self-serve PLG tier", "source": "Product Hunt", "published_date": "2026-01-05", "summary": "New freemium tier driving 3x increase in developer signups.", "category": "product"},
  {"company_id": 9, "title": "Acquires competitor DataMesh", "source": "TechCrunch", "published_date": "2025-12-20", "summary": "Strategic acquisition adds real-time streaming capabilities to analytics platform.", "category": "partnership"},
  {"company_id": 10, "title": "Named a Gartner Cool Vendor", "source": "Gartner", "published_date": "2026-02-15", "summary": "Recognized for innovation in cloud-native observability.", "category": "product"},
  {"company_id": 11, "title": "Closes $30M Series B", "source": "VentureBeat", "published_date": "2025-10-05", "summary": "Funding to expand go-to-market team and enter mid-market segment.", "category": "funding"},
  {"company_id": 12, "title": "Launches carbon tracking API", "source": "GreenBiz", "published_date": "2026-01-12", "summary": "New API enables real-time emissions tracking across supply chains.", "category": "product"},
  {"company_id": 13, "title": "Surpasses 500 enterprise customers", "source": "PR Newswire", "published_date": "2026-02-20", "summary": "Customer count doubles year-over-year with strong net retention.", "category": "product"},
  {"company_id": 14, "title": "Opens Austin engineering hub", "source": "Built In Austin", "published_date": "2025-11-01", "summary": "New office to house 100+ engineers focused on ML infrastructure.", "category": "hiring"},
  {"company_id": 15, "title": "Wins $12M DOD contract", "source": "Federal News Network", "published_date": "2026-01-25", "summary": "Multi-year contract for zero-trust security platform deployment.", "category": "partnership"},
  {"company_id": 16, "title": "Series C at $400M valuation", "source": "Bloomberg", "published_date": "2025-09-15", "summary": "Latest round values company at 20x ARR, signaling strong investor confidence.", "category": "funding"},
  {"company_id": 17, "title": "Launches AI copilot for recruiters", "source": "HR Dive", "published_date": "2026-02-05", "summary": "New AI feature automates candidate screening and scheduling.", "category": "product"},
  {"company_id": 18, "title": "Expands warehouse management suite", "source": "Supply Chain Dive", "published_date": "2025-12-01", "summary": "Added robotics integration and predictive inventory modules.", "category": "product"},
  {"company_id": 19, "title": "Raises $20M to fuel growth", "source": "Crunchbase News", "published_date": "2025-08-20", "summary": "Series B funding to build out customer success and expand internationally.", "category": "funding"},
  {"company_id": 20, "title": "Named to Forbes Cloud 100", "source": "Forbes", "published_date": "2025-10-10", "summary": "Recognized among top private cloud companies for third consecutive year.", "category": "product"},
  {"company_id": 21, "title": "Partners with AWS for marketplace listing", "source": "AWS Blog", "published_date": "2026-01-18", "summary": "Now available on AWS Marketplace, streamlining enterprise procurement.", "category": "partnership"},
  {"company_id": 22, "title": "Q4 revenue up 95% YoY", "source": "Company Blog", "published_date": "2026-01-30", "summary": "Record quarter driven by enterprise deal expansion and new logo growth.", "category": "product"},
  {"company_id": 23, "title": "Hires 50 engineers in Q1", "source": "LinkedIn", "published_date": "2026-02-28", "summary": "Aggressive hiring push focused on AI/ML and platform engineering.", "category": "hiring"},
  {"company_id": 24, "title": "Achieves FedRAMP authorization", "source": "FedScoop", "published_date": "2025-11-20", "summary": "Federal authorization opens significant government sector pipeline.", "category": "product"},
  {"company_id": 25, "title": "Launches in Japan market", "source": "Nikkei Asia", "published_date": "2026-02-12", "summary": "Tokyo office established with key local partnerships.", "category": "partnership"},
  {"company_id": 26, "title": "Series A extension round", "source": "Crunchbase", "published_date": "2025-07-15", "summary": "Added $8M to Series A for product development runway.", "category": "funding"},
  {"company_id": 27, "title": "Customer case study with Fortune 500", "source": "Company Blog", "published_date": "2026-01-08", "summary": "Major retailer reports 40% efficiency gains from implementation.", "category": "product"},
  {"company_id": 28, "title": "Appoints new CFO", "source": "PR Newswire", "published_date": "2025-12-15", "summary": "Former public company CFO joins ahead of potential IPO preparation.", "category": "hiring"},
  {"company_id": 29, "title": "Integrates with Salesforce ecosystem", "source": "AppExchange", "published_date": "2026-02-22", "summary": "Native Salesforce integration drives 2x pipeline velocity.", "category": "product"},
  {"company_id": 30, "title": "Raises Bridge Round", "source": "The Information", "published_date": "2025-06-01", "summary": "Insider-led bridge round to reach profitability milestones.", "category": "funding"}
]
